smooth_logger/LogEntry.py
smooth_logger/Logger.py
smooth_logger/__init__.py
smooth_logger/enums.py
smooth_logger-1.0.3.dist-info/LICENSE
smooth_logger-1.0.3.dist-info/METADATA
smooth_logger-1.0.3.dist-info/WHEEL
smooth_logger-1.0.3.dist-info/top_level.txt
smooth_logger-1.0.3.dist-info/RECORD
