Metadata-Version: 2.1
Name: smooth_logger
Version: 1.0.3
Summary: A simple logger made primarily for my own personal use. Made from a combination of necessity and so much sloth that it overflowed into productivity.
Home-page: https://github.com/MollyMaclachlan/smooth_logger
Author: Molly Maclachlan
Author-email: murdomaclachlan@duck.com
License: AGPLv3+
Classifier: Programming Language :: Python :: 3.5
Classifier: Programming Language :: Python :: 3.7
Classifier: Programming Language :: Python :: 3.8
Classifier: Programming Language :: Python :: 3.9
Classifier: Programming Language :: Python :: 3.10
Classifier: Programming Language :: Python :: 3.11
Classifier: Programming Language :: Python :: 3.12
Classifier: License :: OSI Approved :: GNU Affero General Public License v3 or later (AGPLv3+)
Classifier: Operating System :: OS Independent
License-File: LICENSE
Requires-Dist: plyer
